llm_connect_api/__init__.py
llm_connect_api/cli.py
llm_connect_api/config.py
llm_connect_api/commands/__init__.py
llm_connect_api/commands/add_model.py
llm_connect_api/commands/execute.py
llm_connect_api/commands/fetch_result.py
llm_connect_api/commands/hardware.py
llm_connect_api/commands/list_models.py
llm_connect_api/commands/list_tasks.py
llm_connect_api-1.0.1.dist-info/METADATA
llm_connect_api-1.0.1.dist-info/WHEEL
llm_connect_api-1.0.1.dist-info/entry_points.txt
llm_connect_api-1.0.1.dist-info/top_level.txt
llm_connect_api-1.0.1.dist-info/RECORD
