Metadata-Version: 2.1
Name: llm_connect_api
Version: 1.0.1
Summary: LLM Connect API
Author: CeADAR Connect Group
Requires-Dist: click ==8.1.7
Requires-Dist: setuptools ~=68.2.0
Requires-Dist: transformers ~=4.34.0
Requires-Dist: torch ~=2.1.0
Requires-Dist: accelerate
Requires-Dist: bitsandbytes
Requires-Dist: colorama
